chrys/__init__.py
chrys/palettes.py
chrys/utils.py
chrys/data/__init__.py
chrys/data/bokeh_palettes.py
chrys/data/vega_palettes.py
chrys-4.2.2.dist-info/METADATA
chrys-4.2.2.dist-info/WHEEL
chrys-4.2.2.dist-info/licenses/LICENSE
chrys-4.2.2.dist-info/RECORD
