Metadata-Version: 2.4
Name: chrys
Version: 4.2.2
Summary: A collection of color palettes for mapping and visualisation
License-File: LICENSE
Requires-Python: >=3.10
Requires-Dist: matplotlib>=3.3.2
Requires-Dist: wcag-contrast-ratio>=0.9
